maji_cli-0.0.1.dist-info/LICENSE.txt
maji_cli-0.0.1.dist-info/METADATA
maji_cli-0.0.1.dist-info/RECORD
maji_cli-0.0.1.dist-info/WHEEL
maji_cli-0.0.1.dist-info/top_level.txt
majicli/__init__.py
